controllers/__init__.py
controllers/adder.py
controllers/deleter.py
controllers/editor.py
helpers/countries.py
helpers/inputs.py
helpers/location.py
helpers/patterns.py
helpers/session.py
helpers/table_output.py
helpers/ui.py
helpers/validators.py
helpers/weather.py
input_handlers/__init__.py
input_handlers/add_address.py
input_handlers/add_birthday.py
input_handlers/add_contact.py
input_handlers/add_email.py
input_handlers/add_note.py
input_handlers/add_phone.py
input_handlers/add_tag.py
input_handlers/all_contacts.py
input_handlers/birthdays.py
input_handlers/change_contact.py
input_handlers/delete_note.py
input_handlers/edit_note.py
input_handlers/edit_phone.py
input_handlers/remove_address.py
input_handlers/remove_birthday.py
input_handlers/remove_contact.py
input_handlers/remove_email.py
input_handlers/remove_phone.py
input_handlers/search_contact.py
input_handlers/search_note.py
input_handlers/select_contact.py
input_handlers/show_address.py
input_handlers/show_all_notes.py
input_handlers/show_birthday.py
input_handlers/show_contact.py
input_handlers/show_note.py
input_handlers/sort_notes_by_tag.py
models/__init__.py
models/address.py
models/address_book.py
models/birthday.py
models/email.py
models/field.py
models/name.py
models/note.py
models/notes_manager.py
models/phone.py
models/record.py
venv/bin/rst2html.py
venv/bin/rst2html4.py
venv/bin/rst2html5.py
venv/bin/rst2latex.py
venv/bin/rst2man.py
venv/bin/rst2odt.py
venv/bin/rst2odt_prepstyles.py
venv/bin/rst2pseudoxml.py
venv/bin/rst2s5.py
venv/bin/rst2xetex.py
venv/bin/rst2xml.py
venv/bin/rstpep2html.py
chandler_bot-1.dist-info/METADATA
chandler_bot-1.dist-info/WHEEL
chandler_bot-1.dist-info/entry_points.txt
chandler_bot-1.dist-info/top_level.txt
chandler_bot-1.dist-info/RECORD
