Metadata-Version: 2.1
Name: chandler-bot
Version: 1
Summary: You personal assistant
Home-page: https://github.com/MKuzich/bot
Author: MKuzich
Author-email: chandler-bot@gmail.com
License: MIT
Requires-Dist: markdown
